<?xml version='1.0' encoding='UTF-8' standalone='no'?>
<Database>
    <GameDBStringTable ID="LOC_PTBR_ADDON_HYPOCHONDRIACS">
    
    <LanguageCode>ptbr</LanguageCode>
    <LanguageNameLocalized>Português do Brasil</LanguageNameLocalized>
		
	<Contributors>
    <Name>Galo Doido</Name>
    </Contributors>
		
	<LocalizedStrings>
		
	<GameDBLocalizedString>      <LocID>ADDON_HYPOCHONDRIACS</LocID>                       <Text>Hipocondríacos</Text>  </GameDBLocalizedString>
	
	</LocalizedStrings>
	
	</GameDBStringTable>

</Database>
