<?xml version='1.0' encoding='UTF-8'?>
<Database>
	<GameDBSymptom ID="SYM_NEW_PSY_PSG_PLMI">
		<DescriptionLocID>SYM_NEW_PSY_PSG_PLMI_DESC</DescriptionLocID>
		<DiscomfortLevel>None</DiscomfortLevel>
		<PatientComplains>false</PatientComplains>
		<Hazard>Medium</Hazard>
		<ShameLevel>0</ShameLevel>
		<Examinations>
			<ExaminationRef>EXM_NEW_PSY_PSG</ExaminationRef>
		<ExaminationRef>EXM_NEW_PSY_MSLT</ExaminationRef>
		</Examinations>
		<Treatments>
			<TreatmentRef>TRT_NEW_PSY_PRAMIPEXOLE</TreatmentRef>
		</Treatments>
		<PatientMobility>MOBILE</PatientMobility>
		<IsMainSymptom>true</IsMainSymptom>
		<IconIndex>1</IconIndex>
		<CustomIconBigAssetRef>ASSET_ICON_SYM_NEW_PSY_RLS</CustomIconBigAssetRef>
		<CustomIconSmallAssetRef>ASSET_ICON_SYM_NEW_PSY_RLS_SMALL</CustomIconSmallAssetRef>
	</GameDBSymptom>
	<GameDBSymptom ID="SYM_NEW_PSY_ACUTE_AND_TRANSIENT_PSYCHOTIC_DISORDERS">
		<DescriptionLocID>SYM_NEW_PSY_ACUTE_AND_TRANSIENT_PSYCHOTIC_DISORDERS_DESC</DescriptionLocID>
		<DiscomfortLevel>None</DiscomfortLevel>
		<PatientComplains>false</PatientComplains>
		<Hazard>Medium</Hazard>
		<ShameLevel>0</ShameLevel>
		<Examinations>
			<ExaminationRef>EXM_NEW_PSY_PSYCHIATRIC_EXAMINATION</ExaminationRef>
		<ExaminationRef>EXM_NEW_PSY_PSYCHOMETRIC_SCALES</ExaminationRef>
		</Examinations>
		<Treatments>
			<TreatmentRef>TRT_NEW_PSY_ANTIPSYCHOTIC_DRUG_ARIPIPRAZOLE</TreatmentRef>
		</Treatments>
		<PatientMobility>MOBILE</PatientMobility>
		<IsMainSymptom>true</IsMainSymptom>
		<IconIndex>1</IconIndex>
		<CustomIconBigAssetRef>ASSET_ICON_SYM_NEW_PSY_DIAGNOSIS</CustomIconBigAssetRef>
		<CustomIconSmallAssetRef>ASSET_ICON_SYM_NEW_PSY_DIAGNOSIS_SMALL</CustomIconSmallAssetRef>
	</GameDBSymptom>
	<GameDBSymptom ID="SYM_NEW_PSY_DEPERSONALIZATION_DIA">
		<DescriptionLocID>SYM_NEW_PSY_DEPERSONALIZATION_DIA_DESC</DescriptionLocID>
		<DiscomfortLevel>None</DiscomfortLevel>
		<PatientComplains>false</PatientComplains>
		<Hazard>Medium</Hazard>
		<ShameLevel>0</ShameLevel>
		<Examinations>
			<ExaminationRef>EXM_NEW_PSY_PSYCHIATRIC_EXAMINATION</ExaminationRef>
		<ExaminationRef>EXM_NEW_PSY_PSYCHOMETRIC_SCALES</ExaminationRef>
		</Examinations>
		<Treatments>
			<TreatmentRef>TRT_NEW_PSY_PSYCHOTHERAPY</TreatmentRef>
		</Treatments>
		<PatientMobility>MOBILE</PatientMobility>
		<IsMainSymptom>true</IsMainSymptom>
		<IconIndex>1</IconIndex>
		<CustomIconBigAssetRef>ASSET_ICON_SYM_NEW_PSY_DEPERSONALIZATION</CustomIconBigAssetRef>
		<CustomIconSmallAssetRef>ASSET_ICON_SYM_NEW_PSY_DEPERSONALIZATION_SMALL</CustomIconSmallAssetRef>
	</GameDBSymptom>
	<GameDBSymptom ID="SYM_NEW_PSY_NIGHT-EATING">
		<DescriptionLocID>SYM_NEW_PSY_NIGHT-EATING_DESC</DescriptionLocID>
		<DiscomfortLevel>Medium</DiscomfortLevel>
		<PatientComplains>false</PatientComplains>
		<Hazard>Low</Hazard>
		<ShameLevel>0</ShameLevel>
		<Examinations>
			<ExaminationRef>EXM_NEW_PSY_PSYCHIATRIC_EXAMINATION</ExaminationRef>
		<ExaminationRef>EXM_NEW_PSY_PSYCHOMETRIC_SCALES</ExaminationRef>
		</Examinations>
		<Treatments>
			<TreatmentRef>TRT_NEW_PSY_PSYCHOTHERAPY</TreatmentRef>
		</Treatments>
		<PatientMobility>MOBILE</PatientMobility>
		<IsMainSymptom>true</IsMainSymptom>
		<IconIndex>1</IconIndex>
		<CustomIconBigAssetRef>ASSET_ICON_SYM_NEW_PSY_NIGHT-EATING</CustomIconBigAssetRef>
		<CustomIconSmallAssetRef>ASSET_ICON_SYM_NEW_PSY_NIGHT-EATING_SMALL</CustomIconSmallAssetRef>
	</GameDBSymptom>
	<GameDBSymptom ID="SYM_NEW_PSY_SHIFT_WORK">
		<DescriptionLocID>SYM_NEW_PSY_SHIFT_WORK_DESC</DescriptionLocID>
		<DiscomfortLevel>Medium</DiscomfortLevel>
		<PatientComplains>false</PatientComplains>
		<Hazard>Low</Hazard>
		<ShameLevel>0</ShameLevel>
		<Examinations>
			<ExaminationRef>EXM_EVALUATION</ExaminationRef>
		</Examinations>
		<Treatments>
			<TreatmentRef>TRT_NEW_PSY_SLEEPING_DRUGS_ZS_ESZOPICLONE</TreatmentRef>
		</Treatments>
		<PatientMobility>MOBILE</PatientMobility>
		<IsMainSymptom>true</IsMainSymptom>
		<IconIndex>1</IconIndex>
		<CustomIconBigAssetRef>ASSET_ICON_SYM_NEW_PSY_SHIFT_WORK</CustomIconBigAssetRef>
		<CustomIconSmallAssetRef>ASSET_ICON_SYM_NEW_PSY_SHIFT_WORK_SMALL</CustomIconSmallAssetRef>
	</GameDBSymptom>
	<GameDBSymptom ID="SYM_NEW_PSY_TOBACCO_WITHDRAWAL">
		<DescriptionLocID>SYM_NEW_PSY_TOBACCO_WITHDRAWAL_DESC</DescriptionLocID>
		<DiscomfortLevel>None</DiscomfortLevel>
		<PatientComplains>false</PatientComplains>
		<Hazard>Medium</Hazard>
		<ShameLevel>0</ShameLevel>
		<Examinations>
			<ExaminationRef>EXM_EVALUATION</ExaminationRef>
		</Examinations>
		<Treatments>
			<TreatmentRef>TRT_NEW_PSY_VARENICLINE</TreatmentRef>
		</Treatments>
		<PatientMobility>MOBILE</PatientMobility>
		<IsMainSymptom>true</IsMainSymptom>
		<IconIndex>1</IconIndex>
		<CustomIconBigAssetRef>ASSET_ICON_SYM_NEW_PSY_TOBACCO_WITHDRAWAL</CustomIconBigAssetRef>
		<CustomIconSmallAssetRef>ASSET_ICON_SYM_NEW_PSY_TOBACCO_WITHDRAWAL_SMALL</CustomIconSmallAssetRef>
	</GameDBSymptom>
	<GameDBSymptom ID="SYM_NEW_PSY_TIC_DISORDERS">
		<DescriptionLocID>SYM_NEW_PSY_TIC_DISORDERS_DESC</DescriptionLocID>
		<DiscomfortLevel>None</DiscomfortLevel>
		<PatientComplains>false</PatientComplains>
		<Hazard>Medium</Hazard>
		<ShameLevel>0</ShameLevel>
		<Examinations>
			<ExaminationRef>EXM_NEW_PSY_PSYCHIATRIC_EXAMINATION</ExaminationRef>
		<ExaminationRef>EXM_NEW_PSY_PSYCHOMETRIC_SCALES</ExaminationRef>
		</Examinations>
		<Treatments>
			<TreatmentRef>TRT_NEW_PSY_ANTIPSYCHOTIC_DRUG_ARIPIPRAZOLE</TreatmentRef>
		</Treatments>
		<PatientMobility>MOBILE</PatientMobility>
		<IsMainSymptom>true</IsMainSymptom>
		<IconIndex>1</IconIndex>
		<CustomIconBigAssetRef>ASSET_ICON_SYM_NEW_PSY_INVOLUNTARY_MOVEMENT</CustomIconBigAssetRef>
		<CustomIconSmallAssetRef>ASSET_ICON_SYM_NEW_PSY_INVOLUNTARY_MOVEMENT_SMALL</CustomIconSmallAssetRef>
	</GameDBSymptom>
	<GameDBSymptom ID="SYM_NEW_PSY_ANOREXIA_NERVOSA">
		<DescriptionLocID>SYM_NEW_PSY_ANOREXIA_NERVOSA_DESC</DescriptionLocID>
		<DiscomfortLevel>Medium</DiscomfortLevel>
		<PatientComplains>false</PatientComplains>
		<Hazard>Medium</Hazard>
		<ShameLevel>0</ShameLevel>
		<Examinations>
			<ExaminationRef>EXM_NEW_PSY_PSYCHIATRIC_EXAMINATION</ExaminationRef>
		<ExaminationRef>EXM_NEW_PSY_PSYCHOMETRIC_SCALES</ExaminationRef>
		</Examinations>
		<Treatments>
			<TreatmentRef>TRT_NEW_PSY_PSYCHOTHERAPY</TreatmentRef>
		</Treatments>
		<PatientMobility>MOBILE</PatientMobility>
		<IsMainSymptom>true</IsMainSymptom>
		<IconIndex>1</IconIndex>
		<CustomIconBigAssetRef>ASSET_ICON_SYM_NEW_PSY_ANOREXIA_NERVOSA</CustomIconBigAssetRef>
		<CustomIconSmallAssetRef>ASSET_ICON_SYM_NEW_PSY_ANOREXIA_NERVOSA_SMALL</CustomIconSmallAssetRef>
	</GameDBSymptom>
	<GameDBSymptom ID="SYM_NEW_PSY_MSLT_BARCOLEPSY">
		<DescriptionLocID>SYM_NEW_PSY_MSLT_BARCOLEPSY_DESC</DescriptionLocID>
		<DiscomfortLevel>None</DiscomfortLevel>
		<PatientComplains>false</PatientComplains>
		<Hazard>Medium</Hazard>
		<ShameLevel>0</ShameLevel>
		<Examinations>
			<ExaminationRef>EXM_NEW_PSY_MSLT</ExaminationRef>
		</Examinations>
		<Treatments>
			<TreatmentRef>TRT_NEW_PSY_AWAKENING_PROMOTING_DRUGS_PITOLISANT</TreatmentRef>
		</Treatments>
		<PatientMobility>MOBILE</PatientMobility>
		<IsMainSymptom>true</IsMainSymptom>
		<IconIndex>1</IconIndex>
		<CustomIconBigAssetRef>ASSET_ICON_SYM_NEW_PSY_SLEEP_PARALYSIS</CustomIconBigAssetRef>
		<CustomIconSmallAssetRef>ASSET_ICON_SYM_NEW_PSY_SLEEP_PARALYSIS_SMALL</CustomIconSmallAssetRef>
	</GameDBSymptom>
	<GameDBSymptom ID="SYM_NEW_PSY_LIFE_EVENT">
		<DescriptionLocID>SYM_NEW_PSY_LIFE_EVENT_DESC</DescriptionLocID>
		<DiscomfortLevel>Medium</DiscomfortLevel>
		<PatientComplains>false</PatientComplains>
		<Hazard>Low</Hazard>
		<ShameLevel>0</ShameLevel>
		<Examinations>
			<ExaminationRef>EXM_EVALUATION</ExaminationRef>
		</Examinations>
		<Treatments>
			<TreatmentRef>TRT_NEW_PSY_PSYCHOTHERAPY</TreatmentRef>
		</Treatments>
		<PatientMobility>MOBILE</PatientMobility>
		<IsMainSymptom>true</IsMainSymptom>
		<IconIndex>1</IconIndex>
		<CustomIconBigAssetRef>ASSET_ICON_SYM_NEW_PSY_STRESS_EVENT</CustomIconBigAssetRef>
		<CustomIconSmallAssetRef>ASSET_ICON_SYM_NEW_PSY_STRESS_EVENT_SMALL</CustomIconSmallAssetRef>
	</GameDBSymptom>
	<GameDBSymptom ID="SYM_NEW_PSY_ADHD">
		<DescriptionLocID>SYM_NEW_PSY_ADHD_DESC</DescriptionLocID>
		<DiscomfortLevel>Low</DiscomfortLevel>
		<PatientComplains>false</PatientComplains>
		<Hazard>Medium</Hazard>
		<ShameLevel>0</ShameLevel>
		<Examinations>
			<ExaminationRef>EXM_NEW_PSY_PSYCHIATRIC_EXAMINATION</ExaminationRef>
		<ExaminationRef>EXM_NEW_PSY_PSYCHOMETRIC_SCALES</ExaminationRef>
		</Examinations>
		<Treatments>
			<TreatmentRef>TRT_NEW_PSY_NRIS_TOMOXETINE</TreatmentRef>
		</Treatments>
		<PatientMobility>MOBILE</PatientMobility>
		<IsMainSymptom>true</IsMainSymptom>
		<IconIndex>1</IconIndex>
		<CustomIconBigAssetRef>ASSET_ICON_SYM_NEW_PSY_ADHD</CustomIconBigAssetRef>
		<CustomIconSmallAssetRef>ASSET_ICON_SYM_NEW_PSY_ADHD_SMALL</CustomIconSmallAssetRef>
	</GameDBSymptom>
	<GameDBSymptom ID="SYM_NEW_PSY_HIPPOCAMPAL_ATROPHY">
		<DescriptionLocID>SYM_NEW_PSY_HIPPOCAMPAL_ATROPHY_DESC</DescriptionLocID>
		<DiscomfortLevel>None</DiscomfortLevel>
		<PatientComplains>false</PatientComplains>
		<Hazard>Medium</Hazard>
		<ShameLevel>0</ShameLevel>
		<Examinations>
			<ExaminationRef>EXM_MRI</ExaminationRef>
		</Examinations>
		<Treatments>
			<TreatmentRef>TRT_NEW_PSY_ANTIDEMENTIA_MEDICINE_DONEPEZIL</TreatmentRef>
		</Treatments>
		<PatientMobility>MOBILE</PatientMobility>
		<IsMainSymptom>true</IsMainSymptom>
		<IconIndex>1</IconIndex>
		<CustomIconBigAssetRef>ASSET_ICON_SYM_NEW_PSY_CEREBRAL_ATROPHY</CustomIconBigAssetRef>
		<CustomIconSmallAssetRef>ASSET_ICON_SYM_NEW_PSY_CEREBRAL_ATROPHY_SMALL</CustomIconSmallAssetRef>
	</GameDBSymptom>
	<GameDBSymptom ID="SYM_NEW_PSY_AGRO_PHOBIA">
		<DescriptionLocID>SYM_NEW_PSY_AGRO_PHOBIA_DESC</DescriptionLocID>
		<DiscomfortLevel>Medium</DiscomfortLevel>
		<PatientComplains>false</PatientComplains>
		<Hazard>Medium</Hazard>
		<ShameLevel>0</ShameLevel>
		<Examinations>
			<ExaminationRef>EXM_NEW_PSY_PSYCHIATRIC_EXAMINATION</ExaminationRef>
		<ExaminationRef>EXM_NEW_PSY_PSYCHOMETRIC_SCALES</ExaminationRef>
		</Examinations>
		<Treatments>
			<TreatmentRef>TRT_NEW_PSY_PSYCHOTHERAPY</TreatmentRef>
		</Treatments>
		<PatientMobility>MOBILE</PatientMobility>
		<IsMainSymptom>true</IsMainSymptom>
		<IconIndex>1</IconIndex>
		<CustomIconBigAssetRef>ASSET_ICON_SYM_NEW_PSY_AGRO_PHOBIA</CustomIconBigAssetRef>
		<CustomIconSmallAssetRef>ASSET_ICON_SYM_NEW_PSY_AGRO_PHOBIA_SMALL</CustomIconSmallAssetRef>
	</GameDBSymptom>
	<GameDBSymptom ID="SYM_NEW_PSY_SPECIFIC_PHOBIA">
		<DescriptionLocID>SYM_NEW_PSY_SPECIFIC_PHOBIA_DESC</DescriptionLocID>
		<DiscomfortLevel>Medium</DiscomfortLevel>
		<PatientComplains>false</PatientComplains>
		<Hazard>Medium</Hazard>
		<ShameLevel>0</ShameLevel>
		<Examinations>
			<ExaminationRef>EXM_NEW_PSY_PSYCHIATRIC_EXAMINATION</ExaminationRef>
		<ExaminationRef>EXM_NEW_PSY_PSYCHOMETRIC_SCALES</ExaminationRef>
		</Examinations>
		<Treatments>
			<TreatmentRef>TRT_NEW_PSY_PSYCHOTHERAPY</TreatmentRef>
		</Treatments>
		<PatientMobility>MOBILE</PatientMobility>
		<IsMainSymptom>true</IsMainSymptom>
		<IconIndex>1</IconIndex>
		<CustomIconBigAssetRef>ASSET_ICON_SYM_NEW_PSY_DIAGNOSIS</CustomIconBigAssetRef>
		<CustomIconSmallAssetRef>ASSET_ICON_SYM_NEW_PSY_DIAGNOSIS_SMALL</CustomIconSmallAssetRef>
	</GameDBSymptom>
	<GameDBSymptom ID="SYM_NEW_PSY_SOCIAL_PHOBIA">
		<DescriptionLocID>SYM_NEW_PSY_SOCIAL_PHOBIA_DESC</DescriptionLocID>
		<DiscomfortLevel>Medium</DiscomfortLevel>
		<PatientComplains>false</PatientComplains>
		<Hazard>Medium</Hazard>
		<ShameLevel>0</ShameLevel>
		<Examinations>
			<ExaminationRef>EXM_NEW_PSY_PSYCHIATRIC_EXAMINATION</ExaminationRef>
		<ExaminationRef>EXM_NEW_PSY_PSYCHOMETRIC_SCALES</ExaminationRef>
		</Examinations>
		<Treatments>
			<TreatmentRef>TRT_NEW_PSY_PSYCHOTHERAPY</TreatmentRef>
		</Treatments>
		<PatientMobility>MOBILE</PatientMobility>
		<IsMainSymptom>true</IsMainSymptom>
		<IconIndex>1</IconIndex>
		<CustomIconBigAssetRef>ASSET_ICON_SYM_NEW_PSY_SOCIAL_PHOBIA</CustomIconBigAssetRef>
		<CustomIconSmallAssetRef>ASSET_ICON_SYM_NEW_PSY_SOCIAL_PHOBIA_SMALL</CustomIconSmallAssetRef>
	</GameDBSymptom>
	<GameDBSymptom ID="SYM_NEW_PSY_ALCOHOL_WITHDRAWAL">
		<DescriptionLocID>SYM_NEW_PSY_ALCOHOL_WITHDRAWAL_DESC</DescriptionLocID>
		<DiscomfortLevel>None</DiscomfortLevel>
		<PatientComplains>false</PatientComplains>
		<Hazard>Medium</Hazard>
		<ShameLevel>0</ShameLevel>
		<Examinations>
			<ExaminationRef>EXM_EVALUATION</ExaminationRef>
		</Examinations>
		<Treatments>
			<TreatmentRef>TRT_NEW_PSY_BZs_DIAZEPAM</TreatmentRef>
		</Treatments>
		<PatientMobility>MOBILE</PatientMobility>
		<IsMainSymptom>true</IsMainSymptom>
		<IconIndex>1</IconIndex>
		<CustomIconBigAssetRef>ASSET_ICON_SYM_NEW_PSY_DIAGNOSIS</CustomIconBigAssetRef>
		<CustomIconSmallAssetRef>ASSET_ICON_SYM_NEW_PSY_DIAGNOSIS_SMALL</CustomIconSmallAssetRef>
	</GameDBSymptom>
	<GameDBSymptom ID="SYM_NEW_PSY_SCHIZOPHRENIA">
		<DescriptionLocID>SYM_NEW_PSY_SCHIZOPHRENIA_DESC</DescriptionLocID>
		<DiscomfortLevel>None</DiscomfortLevel>
		<PatientComplains>false</PatientComplains>
		<Hazard>Medium</Hazard>
		<ShameLevel>0</ShameLevel>
		<Examinations>
			<ExaminationRef>EXM_NEW_PSY_PSYCHIATRIC_EXAMINATION</ExaminationRef>
		<ExaminationRef>EXM_NEW_PSY_PSYCHOMETRIC_SCALES</ExaminationRef>
		</Examinations>
		<Treatments>
			<TreatmentRef>TRT_NEW_PSY_ANTIPSYCHOTIC_DRUG_RISPERIDONE</TreatmentRef>
		</Treatments>
		<PatientMobility>MOBILE</PatientMobility>
		<IsMainSymptom>true</IsMainSymptom>
		<IconIndex>1</IconIndex>
		<CustomIconBigAssetRef>ASSET_ICON_SYM_NEW_PSY_DIAGNOSIS</CustomIconBigAssetRef>
		<CustomIconSmallAssetRef>ASSET_ICON_SYM_NEW_PSY_DIAGNOSIS_SMALL</CustomIconSmallAssetRef>
	</GameDBSymptom>
	<GameDBSymptom ID="SYM_NEW_PSY_CHRONIC_INSOMNIA">
		<DescriptionLocID>SYM_NEW_PSY_CHRONIC_INSOMNIA_DESC</DescriptionLocID>
		<DiscomfortLevel>None</DiscomfortLevel>
		<PatientComplains>false</PatientComplains>
		<Hazard>Medium</Hazard>
		<ShameLevel>0</ShameLevel>
		<Examinations>
			<ExaminationRef>EXM_NEW_PSY_PSYCHIATRIC_EXAMINATION</ExaminationRef>
		<ExaminationRef>EXM_NEW_PSY_PSYCHOMETRIC_SCALES</ExaminationRef>
		</Examinations>
		<Treatments>
			<TreatmentRef>TRT_NEW_PSY_SLEEPING_DRUGS_ZS_ESZOPICLONE</TreatmentRef>
		</Treatments>
		<PatientMobility>MOBILE</PatientMobility>
		<IsMainSymptom>true</IsMainSymptom>
		<IconIndex>1</IconIndex>
		<CustomIconBigAssetRef>ASSET_ICON_SYM_NEW_PSY_DIAGNOSIS</CustomIconBigAssetRef>
		<CustomIconSmallAssetRef>ASSET_ICON_SYM_NEW_PSY_DIAGNOSIS_SMALL</CustomIconSmallAssetRef>
	</GameDBSymptom>
	<GameDBSymptom ID="SYM_NEW_PSY_BIPOLAR_DISORDER">
		<DescriptionLocID>SYM_NEW_PSY_BIPOLAR_DISORDER_DESC</DescriptionLocID>
		<DiscomfortLevel>None</DiscomfortLevel>
		<PatientComplains>false</PatientComplains>
		<Hazard>Medium</Hazard>
		<ShameLevel>0</ShameLevel>
		<Examinations>
			<ExaminationRef>EXM_NEW_PSY_PSYCHIATRIC_EXAMINATION</ExaminationRef>
		<ExaminationRef>EXM_NEW_PSY_PSYCHOMETRIC_SCALES</ExaminationRef>
		</Examinations>
		<Treatments>
			<TreatmentRef>TRT_NEW_PSY_MECT</TreatmentRef>
		</Treatments>
		<PatientMobility>MOBILE</PatientMobility>
		<IsMainSymptom>true</IsMainSymptom>
		<IconIndex>1</IconIndex>
		<CustomIconBigAssetRef>ASSET_ICON_SYM_NEW_PSY_DIAGNOSIS</CustomIconBigAssetRef>
		<CustomIconSmallAssetRef>ASSET_ICON_SYM_NEW_PSY_DIAGNOSIS_SMALL</CustomIconSmallAssetRef>
	</GameDBSymptom>
	<GameDBSymptom ID="SYM_NEW_PSY_ACUTE_STRESS_DISORDER">
		<DescriptionLocID>SYM_NEW_PSY_ACUTE_STRESS_DISORDER_DESC</DescriptionLocID>
		<DiscomfortLevel>None</DiscomfortLevel>
		<PatientComplains>false</PatientComplains>
		<Hazard>Medium</Hazard>
		<ShameLevel>0</ShameLevel>
		<Examinations>
			<ExaminationRef>EXM_NEW_PSY_PSYCHIATRIC_EXAMINATION</ExaminationRef>
		<ExaminationRef>EXM_NEW_PSY_PSYCHOMETRIC_SCALES</ExaminationRef>
		</Examinations>
		<Treatments>
			<TreatmentRef>TRT_NEW_PSY_PSYCHOTHERAPY</TreatmentRef>
		</Treatments>
		<PatientMobility>MOBILE</PatientMobility>
		<IsMainSymptom>true</IsMainSymptom>
		<IconIndex>1</IconIndex>
		<CustomIconBigAssetRef>ASSET_ICON_SYM_NEW_PSY_DIAGNOSIS</CustomIconBigAssetRef>
		<CustomIconSmallAssetRef>ASSET_ICON_SYM_NEW_PSY_DIAGNOSIS_SMALL</CustomIconSmallAssetRef>
	</GameDBSymptom>
	<GameDBSymptom ID="SYM_NEW_PSY_PTSD">
		<DescriptionLocID>SYM_NEW_PSY_PTSD_DESC</DescriptionLocID>
		<DiscomfortLevel>None</DiscomfortLevel>
		<PatientComplains>false</PatientComplains>
		<Hazard>Medium</Hazard>
		<ShameLevel>0</ShameLevel>
		<Examinations>
			<ExaminationRef>EXM_NEW_PSY_PSYCHIATRIC_EXAMINATION</ExaminationRef>
		<ExaminationRef>EXM_NEW_PSY_PSYCHOMETRIC_SCALES</ExaminationRef>
		</Examinations>
		<Treatments>
			<TreatmentRef>TRT_NEW_PSY_PSYCHOTHERAPY</TreatmentRef>
		</Treatments>
		<PatientMobility>MOBILE</PatientMobility>
		<IsMainSymptom>true</IsMainSymptom>
		<IconIndex>1</IconIndex>
		<CustomIconBigAssetRef>ASSET_ICON_SYM_NEW_PSY_DIAGNOSIS</CustomIconBigAssetRef>
		<CustomIconSmallAssetRef>ASSET_ICON_SYM_NEW_PSY_DIAGNOSIS_SMALL</CustomIconSmallAssetRef>
	</GameDBSymptom>
	<GameDBSymptom ID="SYM_NEW_PSY_OBSESSIVE-COMPULSIVE_DISORDER">
		<DescriptionLocID>SYM_NEW_PSY_OBSESSIVE-COMPULSIVE_DISORDER_DESC</DescriptionLocID>
		<DiscomfortLevel>Medium</DiscomfortLevel>
		<PatientComplains>false</PatientComplains>
		<Hazard>Medium</Hazard>
		<ShameLevel>0</ShameLevel>
		<Examinations>
			<ExaminationRef>EXM_NEW_PSY_PSYCHIATRIC_EXAMINATION</ExaminationRef>
		<ExaminationRef>EXM_NEW_PSY_PSYCHOMETRIC_SCALES</ExaminationRef>
		</Examinations>
		<Treatments>
			<TreatmentRef>TRT_NEW_PSY_ANTIDEPRESSSANT_DRUGS_SSRIS_FLUOXETINE</TreatmentRef>
		</Treatments>
		<PatientMobility>MOBILE</PatientMobility>
		<IsMainSymptom>true</IsMainSymptom>
		<IconIndex>1</IconIndex>
		<CustomIconBigAssetRef>ASSET_ICON_SYM_NEW_PSY_DIAGNOSIS</CustomIconBigAssetRef>
		<CustomIconSmallAssetRef>ASSET_ICON_SYM_NEW_PSY_DIAGNOSIS_SMALL</CustomIconSmallAssetRef>
	</GameDBSymptom>
	<GameDBSymptom ID="SYM_NEW_PSY_GENERALIZED_ANXIETY_DISORDER">
		<DescriptionLocID>SYM_NEW_PSY_GENERALIZED_ANXIETY_DISORDER_DESC</DescriptionLocID>
		<DiscomfortLevel>None</DiscomfortLevel>
		<PatientComplains>false</PatientComplains>
		<Hazard>Medium</Hazard>
		<ShameLevel>0</ShameLevel>
		<Examinations>
			<ExaminationRef>EXM_NEW_PSY_PSYCHIATRIC_EXAMINATION</ExaminationRef>
		<ExaminationRef>EXM_NEW_PSY_PSYCHOMETRIC_SCALES</ExaminationRef>
		</Examinations>
		<Treatments>
			<TreatmentRef>TRT_NEW_PSY_ANTIDEPRESSSANT_DRUGS_SSRIS_SERTRALINE</TreatmentRef>
		</Treatments>
		<PatientMobility>MOBILE</PatientMobility>
		<IsMainSymptom>true</IsMainSymptom>
		<IconIndex>1</IconIndex>
		<CustomIconBigAssetRef>ASSET_ICON_SYM_NEW_PSY_DIAGNOSIS</CustomIconBigAssetRef>
		<CustomIconSmallAssetRef>ASSET_ICON_SYM_NEW_PSY_DIAGNOSIS_SMALL</CustomIconSmallAssetRef>
	</GameDBSymptom>
	<GameDBSymptom ID="SYM_NEW_PSY_SOMATIC_SYMPTOM_DISORDER">
		<DescriptionLocID>SYM_NEW_PSY_SOMATIC_SYMPTOM_DISORDER_DESC</DescriptionLocID>
		<DiscomfortLevel>None</DiscomfortLevel>
		<PatientComplains>false</PatientComplains>
		<Hazard>Medium</Hazard>
		<ShameLevel>0</ShameLevel>
		<Examinations>
			<ExaminationRef>EXM_NEW_PSY_PSYCHIATRIC_EXAMINATION</ExaminationRef>
		<ExaminationRef>EXM_NEW_PSY_PSYCHOMETRIC_SCALES</ExaminationRef>
		</Examinations>
		<Treatments>
			<TreatmentRef>TRT_NEW_PSY_PSYCHOTHERAPY</TreatmentRef>
		</Treatments>
		<PatientMobility>MOBILE</PatientMobility>
		<IsMainSymptom>true</IsMainSymptom>
		<IconIndex>1</IconIndex>
		<CustomIconBigAssetRef>ASSET_ICON_SYM_NEW_PSY_DIAGNOSIS</CustomIconBigAssetRef>
		<CustomIconSmallAssetRef>ASSET_ICON_SYM_NEW_PSY_DIAGNOSIS_SMALL</CustomIconSmallAssetRef>
	</GameDBSymptom>
	<GameDBSymptom ID="SYM_NEW_PSY_MAJOR_DEPRESSIVE_DISORDER">
		<DescriptionLocID>SYM_NEW_PSY_MAJOR_DEPRESSIVE_DISORDER_DESC</DescriptionLocID>
		<DiscomfortLevel>None</DiscomfortLevel>
		<PatientComplains>false</PatientComplains>
		<Hazard>Medium</Hazard>
		<ShameLevel>0</ShameLevel>
		<Examinations>
			<ExaminationRef>EXM_NEW_PSY_PSYCHIATRIC_EXAMINATION</ExaminationRef>
		<ExaminationRef>EXM_NEW_PSY_PSYCHOMETRIC_SCALES</ExaminationRef>
		</Examinations>
		<Treatments>
			<TreatmentRef>TRT_NEW_PSY_MECT</TreatmentRef>
		</Treatments>
		<PatientMobility>MOBILE</PatientMobility>
		<IsMainSymptom>true</IsMainSymptom>
		<IconIndex>1</IconIndex>
		<CustomIconBigAssetRef>ASSET_ICON_SYM_NEW_PSY_DIAGNOSIS</CustomIconBigAssetRef>
		<CustomIconSmallAssetRef>ASSET_ICON_SYM_NEW_PSY_DIAGNOSIS_SMALL</CustomIconSmallAssetRef>
	</GameDBSymptom>
	<GameDBSymptom ID="SYM_NEW_PSY_PANIC_ATTACK">
		<DescriptionLocID>SYM_NEW_PSY_PANIC_ATTACK_DESC</DescriptionLocID>
		<DiscomfortLevel>High</DiscomfortLevel>
		<PatientComplains>false</PatientComplains>
		<Hazard>Medium</Hazard>
		<ShameLevel>0</ShameLevel>
		<Examinations>
			<ExaminationRef>EXM_NEW_PSY_PSYCHIATRIC_EXAMINATION</ExaminationRef>
		<ExaminationRef>EXM_NEW_PSY_PSYCHOMETRIC_SCALES</ExaminationRef>
		</Examinations>
		<Treatments>
			<TreatmentRef>TRT_NEW_PSY_BZs_LORAZEPAM</TreatmentRef>
		</Treatments>
		<PatientMobility>MOBILE</PatientMobility>
		<IsMainSymptom>true</IsMainSymptom>
		<IconIndex>1</IconIndex>
		<CustomIconBigAssetRef>ASSET_ICON_SYM_NEW_PSY_PANIC_ATTACK</CustomIconBigAssetRef>
		<CustomIconSmallAssetRef>ASSET_ICON_SYM_NEW_PSY_PANIC_ATTACK_SMALL</CustomIconSmallAssetRef>
	</GameDBSymptom>
</Database>