<?xml version='1.0' encoding='UTF-8' standalone='no'?>
<Database>
    <GameDBStringTable ID="LOC_TR_ADDON_SEXUAL_HEALTH">
    
    <LanguageCode>tr</LanguageCode>
    <LanguageNameLocalized>Türkçe</LanguageNameLocalized>
		
	<Contributors>
    <Name>xburcus</Name>
    </Contributors>
		
	<LocalizedStrings>
		
		<GameDBLocalizedString>      <LocID>ADDON_SEXUAL_HEALTH</LocID>																<Text>Cinsel Sağlık</Text>  </GameDBLocalizedString>
	
	
		<GameDBLocalizedString>      <LocID>ADDON_OBJECT_DECAL_SEX_HEALTH</LocID>											<Text>Cinsel Sağlık</Text>  </GameDBLocalizedString>
		<GameDBLocalizedString>      <LocID>ADDON_OBJECT_DECAL_SEX_HEALTH_DESCRIPTION</LocID>					<Text>Duvar çıkartması.</Text>  </GameDBLocalizedString>

    <GameDBLocalizedString>      <LocID>ADDON_OBJECT_SEX_HEALTH_POSTER_A</LocID>									<Text>Poster - Viral</Text>    </GameDBLocalizedString>
    <GameDBLocalizedString>      <LocID>ADDON_OBJECT_SEX_HEALTH_POSTER_A_DESCRIPTION</LocID>      <Text>Sıkılmış hastların göz atabileceği bir dekorasyon.</Text>    </GameDBLocalizedString>

    <GameDBLocalizedString>      <LocID>ADDON_OBJECT_SEX_HEALTH_POSTER_B</LocID>									<Text>Poster - jenital</Text>    </GameDBLocalizedString>
    <GameDBLocalizedString>      <LocID>ADDON_OBJECT_SEX_HEALTH_POSTER_B_DESCRIPTION</LocID>      <Text>Sıkılmış hastların göz atabileceği bir dekorasyon.</Text>    </GameDBLocalizedString>
	
	</LocalizedStrings>
	
	</GameDBStringTable>

</Database>
