<?xml version='1.0' encoding='UTF-8' standalone='no'?>
<Database>
    <GameDBStringTable ID="LOC_NL_ADDON_SEXUAL_HEALTH_SYMPTOMS">

        <LanguageCode>nl</LanguageCode>
        <LanguageNameLocalized>Nederlands</LanguageNameLocalized>

        <Contributors>
            <Name>Spookiieej</Name>
        </Contributors>

        <LocalizedStrings>

			

			<GameDBLocalizedString>
				<LocID>SYM_SH_GENITAL_DISCHARGE</LocID>
				<Text>Genitale afscheiding</Text>
			</GameDBLocalizedString>
			<GameDBLocalizedString>
				<LocID>SYM_SH_GENITAL_DISCHARGE_DESCRIPTION</LocID>
				<Text>Ongewone afscheiding van de vagina, penis of kont.</Text>
			</GameDBLocalizedString>
			<GameDBLocalizedString>
				<LocID>SYM_SH_PUBIC_LICE</LocID>
				<Text>Schaamluis aanwezig</Text>
			</GameDBLocalizedString>
			<GameDBLocalizedString>
				<LocID>SYM_SH_PUBIC_LICE_DESCRIPTION</LocID>
				<Text>Schaamluis aanwezig in het schaamhaar.</Text>
			</GameDBLocalizedString>
			<GameDBLocalizedString>
				<LocID>SYM_SH_NEISSERIA_GONORRHOEAE</LocID>
				<Text>Neisseria Gonorrhoeae gedetecteerd.</Text>
			</GameDBLocalizedString>
			<GameDBLocalizedString>
				<LocID>SYM_SH_NEISSERIA_GONORRHOEAE_DESCRIPTION</LocID>
				<Text>Testen hebben de Neisseria Gonorrhoeae bacterie ontdekt.</Text>
			</GameDBLocalizedString>
			<GameDBLocalizedString>
				<LocID>SYM_SH_CHLAMYDIA</LocID>
				<Text>Chlamydia gedetecteerd.</Text>
			</GameDBLocalizedString>
			<GameDBLocalizedString>
				<LocID>SYM_SH_CHLAMYDIA_DESCRIPTION</LocID>
				<Text>Testen hebben de chlamydia bacterie ontdekt.</Text>
			</GameDBLocalizedString>
			<GameDBLocalizedString>
				<LocID>SYM_SH_GENITAL_SORES</LocID>
				<Text>Genitale zweren</Text>
			</GameDBLocalizedString>
			<GameDBLocalizedString>
				<LocID>SYM_SH_GENITAL_SORES_DESCRIPTION</LocID>
				<Text>Zweren, wratten of blaasjes die normaal verschijnen op de penis, de balzak, de vagina, de vulva of rond de anus.</Text>
			</GameDBLocalizedString>
			<GameDBLocalizedString>
				<LocID>SYM_SH_SYPHILIS</LocID>
				<Text>Syfilis gedetecteerd.</Text>
			</GameDBLocalizedString>
			<GameDBLocalizedString>
				<LocID>SYM_SH_SYPHILIS_DESCRIPTION</LocID>
				<Text>Testen hebben de syfilis bacterie ontdekt.</Text>
			</GameDBLocalizedString>
			<GameDBLocalizedString>
				<LocID>SYM_SH_HIV</LocID>
				<Text>HIV gedetecteerd</Text>
			</GameDBLocalizedString>
			<GameDBLocalizedString>
				<LocID>SYM_SH_HIV_DESCRIPTION</LocID>
				<Text>Testen hebben ‘Human Immunodeficiency Virus’ ondekt.</Text>
			</GameDBLocalizedString>
			<GameDBLocalizedString>
				<LocID>SYM_SH_HSV</LocID>
				<Text>Herpes antilichamen gedetecteerd.</Text>
			</GameDBLocalizedString>
			<GameDBLocalizedString>
				<LocID>SYM_SH_HSV_DESCRIPTION</LocID>
				<Text>Testen hebben de aanwezigheid van antilichamen tegen het Herpes Simplex Virus ontdekt.</Text>
			</GameDBLocalizedString>
			<GameDBLocalizedString>
				<LocID>SYM_SH_SCABIES</LocID>
				<Text>Schruft gedetecteerd</Text>
			</GameDBLocalizedString>
			<GameDBLocalizedString>
				<LocID>SYM_SH_SCABIES_DESCRIPTION</LocID>
				<Text>Mijten, eieren of holle lijnen hebben de aanwezigheid van schutft geïndiceerd.</Text>
			</GameDBLocalizedString>
			<GameDBLocalizedString>
				<LocID>SYM_SH_HPV</LocID>
				<Text>HPV gedetecteerd</Text>
			</GameDBLocalizedString>
			<GameDBLocalizedString>
				<LocID>SYM_SH_HPV_DESCRIPTION</LocID>
				<Text>Genitale screening heeft de aanwezigheid van humaan papillomavirus aangetoond.</Text>
			</GameDBLocalizedString>
			<GameDBLocalizedString>
				<LocID>SYM_SH_MCI</LocID>
				<Text>MC gedetecteerd</Text>
			</GameDBLocalizedString>
			<GameDBLocalizedString>
				<LocID>SYM_SH_MCI_DESCRIPTION</LocID>
				<Text>Fysiek onderzoek heeft de aanwezigheid van MC aangetoond.</Text>
			</GameDBLocalizedString>
			<GameDBLocalizedString>
				<LocID>SYM_SH_TV</LocID>
				<Text>TV gedetecteerd.</Text>
			</GameDBLocalizedString>
			<GameDBLocalizedString>
				<LocID>SYM_SH_TV_DESCRIPTION</LocID>
				<Text>Analyse van het genitale uitstrijkje heeft de aanwezigheid van het Trichomoniasis virus aangetoond.</Text>
			</GameDBLocalizedString>
			<GameDBLocalizedString>
				<LocID>SYM_SH_BV</LocID>
				<Text>VS gedetecteerd</Text>
			</GameDBLocalizedString>
			<GameDBLocalizedString>
				<LocID>SYM_SH_BV_DESCRIPTION</LocID>
				<Text>Analyse van het genitale uitstrijkje heeft de aanwezigheid van een vaginale schimmelinfectie aangetoond.</Text>
			</GameDBLocalizedString>
			<GameDBLocalizedString>
				<LocID>SYM_SH_CERVICITIS</LocID>
				<Text>Cervicitis detected</Text>
			</GameDBLocalizedString>
			<GameDBLocalizedString>
				<LocID>SYM_SH_CERVICITIS_DESCRIPTION</LocID>
				<Text>Analyse van het genitale uitstrijkje heeft cervicitis aangetoond.</Text>
			</GameDBLocalizedString>
			<GameDBLocalizedString>
				<LocID>SYM_SH_VAGINAL_BLEEDING</LocID>
				<Text>Abnormale vaginale bloeding</Text>
			</GameDBLocalizedString>
			<GameDBLocalizedString>
				<LocID>SYM_SH_VAGINAL_BLEEDING_DESCRIPTION</LocID>
				<Text>Vaginale bloeding buiten de menstruele cyclus.</Text>
			</GameDBLocalizedString>
			<GameDBLocalizedString>
				<LocID>SYM_SH_SEX_PAIN</LocID>
				<Text>Pijn gedurende seks</Text>
			</GameDBLocalizedString>
			<GameDBLocalizedString>
				<LocID>SYM_SH_SEX_PAIN_DESCRIPTION</LocID>
				<Text>De patiënt ervaart pijn tijdens geslachtsgemeenschap.</Text>
			</GameDBLocalizedString>
			<GameDBLocalizedString>
				<LocID>SYM_SH_MGEN_FEMALE</LocID>
				<Text>Mgen detected</Text>
			</GameDBLocalizedString>
			<GameDBLocalizedString>
				<LocID>SYM_SH_MGEN_FEMALE_DESCRIPTION</LocID>
				<Text>Testen hebben de aanwezigheid van mycoplasma genitalium aangetoond.</Text>
			</GameDBLocalizedString>
			<GameDBLocalizedString>
				<LocID>SYM_SH_MGEN_MALE</LocID>
				<Text>Mgen detected</Text>
			</GameDBLocalizedString>
			<GameDBLocalizedString>
				<LocID>SYM_SH_MGEN_MALE_DESCRIPTION</LocID>
				<Text>Testen hebben de aanwezigheid van mycoplasma genitalium aangetoond.</Text>
			</GameDBLocalizedString>
			<GameDBLocalizedString>
				<LocID>SYM_SH_TESTICULAR_PAIN</LocID>
				<Text>Testikelpijn</Text>
			</GameDBLocalizedString>
			<GameDBLocalizedString>
				<LocID>SYM_SH_TESTICULAR_PAIN_DESCRIPTION</LocID>
				<Text>De patiënt ervaart pijn aan de testikels.</Text>
			</GameDBLocalizedString>
			<GameDBLocalizedString>
				<LocID>SYM_SH_PREP</LocID>
				<Text>At risk</Text>
			</GameDBLocalizedString>
			<GameDBLocalizedString>
				<LocID>SYM_SH_PREP_DESCRIPTION</LocID>
				<Text>The patient is at high risk of HIV. Reasons can include sexuality, drug use or serodiscordant relationships.</Text>
			</GameDBLocalizedString>
			<GameDBLocalizedString>
				<LocID>SYM_SH_UR</LocID>
				<Text>Urethritis</Text>
			</GameDBLocalizedString>
			<GameDBLocalizedString>
				<LocID>SYM_SH_UR_DESCRIPTION</LocID>
				<Text>Tests have shown the patient has urethritis.</Text>
			</GameDBLocalizedString>
			<GameDBLocalizedString>
				<LocID>SYM_SH_ED</LocID>
				<Text>Erectile dysfunction</Text>
			</GameDBLocalizedString>
			<GameDBLocalizedString>
				<LocID>SYM_SH_ED_DESCRIPTION</LocID>
				<Text>The patient struggles to achieve or maintain an erection.</Text>
			</GameDBLocalizedString>
			<GameDBLocalizedString>
				<LocID>SYM_SH_EXCESS_SEMEN</LocID>
				<Text>High semen volume</Text>
			</GameDBLocalizedString>
			<GameDBLocalizedString>
				<LocID>SYM_SH_EXCESS_SEMEN_DESCRIPTION</LocID>
				<Text>The patient reports an abnormally large ejaculate (or semen) volume.</Text>
			</GameDBLocalizedString>
			<GameDBLocalizedString>
				<LocID>SYM_SH_HYPERS</LocID>
				<Text>Hyperspermia</Text>
			</GameDBLocalizedString>
			<GameDBLocalizedString>
				<LocID>SYM_SH_HYPERS_DESCRIPTION</LocID>
				<Text>Tests have shown the patient has hyperspermia.</Text>
			</GameDBLocalizedString>
			<GameDBLocalizedString>
				<LocID>SYM_SH_LOW_SEMEN</LocID>
				<Text>Low semen volume</Text>
			</GameDBLocalizedString>
			<GameDBLocalizedString>
				<LocID>SYM_SH_LOW_SEMEN_DESCRIPTION</LocID>
				<Text>The patient reports an unusually low ejaculate (or semen) volume.</Text>
			</GameDBLocalizedString>
			<GameDBLocalizedString>
				<LocID>SYM_SH_HYPOS</LocID>
				<Text>Hypospermia</Text>
			</GameDBLocalizedString>
			<GameDBLocalizedString>
				<LocID>SYM_SH_HYPOS_DESCRIPTION</LocID>
				<Text>Tests have shown the patient has hypospermia.</Text>
			</GameDBLocalizedString>
			<GameDBLocalizedString>
				<LocID>SYM_SH_EPI</LocID>
				<Text>Epididymitis</Text>
			</GameDBLocalizedString>
			<GameDBLocalizedString>
				<LocID>SYM_SH_EPI_DESCRIPTION</LocID>
				<Text>Tests have shown the patient has epididymitis.</Text>
			</GameDBLocalizedString>
			<GameDBLocalizedString>
				<LocID>SYM_SH_PHIMOSIS</LocID>
				<Text>Phimosis</Text>
			</GameDBLocalizedString>
			<GameDBLocalizedString>
				<LocID>SYM_SH_PHIMOSIS_DESCRIPTION</LocID>
				<Text>Phimosis is a condition where the foreskin is too tight to be pulled back over the head of the penis (glans).</Text>
			</GameDBLocalizedString>
			<GameDBLocalizedString>
				<LocID>SYM_SH_BAL</LocID>
				<Text>Balanitis</Text>
			</GameDBLocalizedString>
			<GameDBLocalizedString>
				<LocID>SYM_SH_BAL_DESCRIPTION</LocID>
				<Text>A groin examination has shown the patient has balanitis.</Text>
			</GameDBLocalizedString>
			<GameDBLocalizedString>
				<LocID>SYM_SH_PRO</LocID>
				<Text>Prostatitis</Text>
			</GameDBLocalizedString>
			<GameDBLocalizedString>
				<LocID>SYM_SH_PRO_DESCRIPTION</LocID>
				<Text>Tests have shown the patient has prostatitis.</Text>
			</GameDBLocalizedString>
		
		</LocalizedStrings>
    </GameDBStringTable>
</Database>
