<?xml version='1.0' encoding='UTF-8' standalone='no'?>
<Database>
	<GameDBStringTable ID="LOC_ZHHANS_ADDON_SEXUAL_HEALTH_SYMPTOMS">

		<LanguageCode>zh-Hans</LanguageCode>
		<LanguageNameLocalized>简体中文</LanguageNameLocalized>

		<Contributors>
			<Name>iVincentDong</Name>
			<Name>ChrYue</Name>
			<Name>GreenTheRabbit</Name>
		</Contributors>

		<LocalizedStrings>

			<GameDBLocalizedString>
				<LocID>SYM_SH_GENITAL_DISCHARGE</LocID>
				<Text>生殖器分泌物</Text>
			</GameDBLocalizedString>
			<GameDBLocalizedString>
				<LocID>SYM_SH_GENITAL_DISCHARGE_DESCRIPTION</LocID>
				<Text>从阴道，阴茎或肛门异常排出。</Text>
			</GameDBLocalizedString>
			<GameDBLocalizedString>
				<LocID>SYM_SH_PUBIC_LICE</LocID>
				<Text>检测到阴虱</Text>
			</GameDBLocalizedString>
			<GameDBLocalizedString>
				<LocID>SYM_SH_PUBIC_LICE_DESCRIPTION</LocID>
				<Text>检查显示患者阴毛中存在阴虱。</Text>
			</GameDBLocalizedString>
			<GameDBLocalizedString>
				<LocID>SYM_SH_NEISSERIA_GONORRHOEAE</LocID>
				<Text>检测到淋病病毒</Text>
			</GameDBLocalizedString>
			<GameDBLocalizedString>
				<LocID>SYM_SH_NEISSERIA_GONORRHOEAE_DESCRIPTION</LocID>
				<Text>检查显示患者感染淋病。</Text>
			</GameDBLocalizedString>
			<GameDBLocalizedString>
				<LocID>SYM_SH_CHLAMYDIA</LocID>
				<Text>检测到衣原体病毒</Text>
			</GameDBLocalizedString>
			<GameDBLocalizedString>
				<LocID>SYM_SH_CHLAMYDIA_DESCRIPTION</LocID>
				<Text>检查显示患者感染衣原体。</Text>
			</GameDBLocalizedString>
			<GameDBLocalizedString>
				<LocID>SYM_SH_GENITAL_SORES</LocID>
				<Text>生殖器疮</Text>
			</GameDBLocalizedString>
			<GameDBLocalizedString>
				<LocID>SYM_SH_GENITAL_SORES_DESCRIPTION</LocID>
				<Text>检查显示患者在在阴茎，阴囊，阴道，外阴或肛门周围出现明显的疮，疣或溃疡。</Text>
			</GameDBLocalizedString>
			<GameDBLocalizedString>
				<LocID>SYM_SH_SYPHILIS</LocID>
				<Text>检测到梅毒病毒</Text>
			</GameDBLocalizedString>
			<GameDBLocalizedString>
				<LocID>SYM_SH_SYPHILIS_DESCRIPTION</LocID>
				<Text>检查显示患者感染梅毒。</Text>
			</GameDBLocalizedString>
			<GameDBLocalizedString>
				<LocID>SYM_SH_HIV</LocID>
				<Text>检测到艾滋病毒</Text>
			</GameDBLocalizedString>
			<GameDBLocalizedString>
				<LocID>SYM_SH_HIV_DESCRIPTION</LocID>
				<Text>检查显示患者感染艾滋病毒。</Text>
			</GameDBLocalizedString>
			<GameDBLocalizedString>
				<LocID>SYM_SH_HSV</LocID>
				<Text>检测到单纯疱疹病毒</Text>
			</GameDBLocalizedString>
			<GameDBLocalizedString>
				<LocID>SYM_SH_HSV_DESCRIPTION</LocID>
				<Text>检查显示患者存在抗单纯疱疹病毒的抗体。</Text>
			</GameDBLocalizedString>
			<GameDBLocalizedString>
				<LocID>SYM_SH_SCABIES</LocID>
				<Text>检测到疮</Text>
			</GameDBLocalizedString>
			<GameDBLocalizedString>
				<LocID>SYM_SH_SCABIES_DESCRIPTION</LocID>
				<Text>检查显示患者存在疮。</Text>
			</GameDBLocalizedString>
			<GameDBLocalizedString>
				<LocID>SYM_SH_HPV</LocID>
				<Text>检测到人乳头瘤病毒</Text>
			</GameDBLocalizedString>
			<GameDBLocalizedString>
				<LocID>SYM_SH_HPV_DESCRIPTION</LocID>
				<Text>检查显示患者感染人乳头瘤病毒。</Text>
			</GameDBLocalizedString>
			<GameDBLocalizedString>
				<LocID>SYM_SH_MCI</LocID>
				<Text>检测到MC</Text>
			</GameDBLocalizedString>
			<GameDBLocalizedString>
				<LocID>SYM_SH_MCI_DESCRIPTION</LocID>
				<Text>体格检查显示存在MC。</Text>
			</GameDBLocalizedString>
			<GameDBLocalizedString>
				<LocID>SYM_SH_TV</LocID>
				<Text>检测到TV</Text>
			</GameDBLocalizedString>
			<GameDBLocalizedString>
				<LocID>SYM_SH_TV_DESCRIPTION</LocID>
				<Text>生殖器拭子分析表明存在滴虫病毒。</Text>
			</GameDBLocalizedString>
			<GameDBLocalizedString>
				<LocID>SYM_SH_BV</LocID>
				<Text>检测到BV</Text>
			</GameDBLocalizedString>
			<GameDBLocalizedString>
				<LocID>SYM_SH_BV_DESCRIPTION</LocID>
				<Text>生殖器拭子分析结果表示存在细菌性阴道病。</Text>
			</GameDBLocalizedString>
			<GameDBLocalizedString>
				<LocID>SYM_SH_CERVICITIS</LocID>
				<Text>检测到宫颈炎</Text>
			</GameDBLocalizedString>
			<GameDBLocalizedString>
				<LocID>SYM_SH_CERVICITIS_DESCRIPTION</LocID>
				<Text>生殖器拭子分析结果表示存在宫颈炎。</Text>
			</GameDBLocalizedString>
			<GameDBLocalizedString>
				<LocID>SYM_SH_VAGINAL_BLEEDING</LocID>
				<Text>阴道异常出血</Text>
			</GameDBLocalizedString>
			<GameDBLocalizedString>
				<LocID>SYM_SH_VAGINAL_BLEEDING_DESCRIPTION</LocID>
				<Text>月经周期以外发生的阴道出血。</Text>
			</GameDBLocalizedString>
			<GameDBLocalizedString>
				<LocID>SYM_SH_SEX_PAIN</LocID>
				<Text>性爱疼痛</Text>
			</GameDBLocalizedString>
			<GameDBLocalizedString>
				<LocID>SYM_SH_SEX_PAIN_DESCRIPTION</LocID>
				<Text>患者在性交过程中会感到疼痛。</Text>
			</GameDBLocalizedString>
			<GameDBLocalizedString>
				<LocID>SYM_SH_MGEN_FEMALE</LocID>
				<Text>检测到Mgen</Text>
			</GameDBLocalizedString>
			<GameDBLocalizedString>
				<LocID>SYM_SH_MGEN_FEMALE_DESCRIPTION</LocID>
				<Text>测试显示存在生殖道霉浆菌。</Text>
			</GameDBLocalizedString>
			<GameDBLocalizedString>
				<LocID>SYM_SH_MGEN_MALE</LocID>
				<Text>检测到Mgen</Text>
			</GameDBLocalizedString>
			<GameDBLocalizedString>
				<LocID>SYM_SH_MGEN_MALE_DESCRIPTION</LocID>
				<Text>测试显示存在生殖道霉浆菌。</Text>
			</GameDBLocalizedString>
			<GameDBLocalizedString>
				<LocID>SYM_SH_TESTICULAR_PAIN</LocID>
				<Text>睾丸疼痛</Text>
			</GameDBLocalizedString>
			<GameDBLocalizedString>
				<LocID>SYM_SH_TESTICULAR_PAIN_DESCRIPTION</LocID>
				<Text>患者偶尔会睾丸疼痛。</Text>
			</GameDBLocalizedString>
			<GameDBLocalizedString>
				<LocID>SYM_SH_PREP</LocID>
				<Text>面临风险</Text>
			</GameDBLocalizedString>
			<GameDBLocalizedString>
				<LocID>SYM_SH_PREP_DESCRIPTION</LocID>
				<Text>患者感染艾滋病毒的风险很高。原因可能包括性行为、吸毒或血清不一致的关系。</Text>
			</GameDBLocalizedString>
			<GameDBLocalizedString>
				<LocID>SYM_SH_UR</LocID>
				<Text>尿道炎</Text>
			</GameDBLocalizedString>
			<GameDBLocalizedString>
				<LocID>SYM_SH_UR_DESCRIPTION</LocID>
				<Text>检查结果显示患者患有尿道炎。</Text>
			</GameDBLocalizedString>
			<GameDBLocalizedString>
				<LocID>SYM_SH_ED</LocID>
				<Text>阴茎勃起功能障碍</Text>
			</GameDBLocalizedString>
			<GameDBLocalizedString>
				<LocID>SYM_SH_ED_DESCRIPTION</LocID>
				<Text>患者很难达到或维持勃起。</Text>
			</GameDBLocalizedString>
			<GameDBLocalizedString>
				<LocID>SYM_SH_EXCESS_SEMEN</LocID>
				<Text>精液量异常增多</Text>
			</GameDBLocalizedString>
			<GameDBLocalizedString>
				<LocID>SYM_SH_EXCESS_SEMEN_DESCRIPTION</LocID>
				<Text>患者报告射精（或精液）量异常增多。</Text>
			</GameDBLocalizedString>
			<GameDBLocalizedString>
				<LocID>SYM_SH_HYPERS</LocID>
				<Text>精子增多症</Text>
			</GameDBLocalizedString>
			<GameDBLocalizedString>
				<LocID>SYM_SH_HYPERS_DESCRIPTION</LocID>
				<Text>检查结果显示患者患有精子增多症.</Text>
			</GameDBLocalizedString>
			<GameDBLocalizedString>
				<LocID>SYM_SH_LOW_SEMEN</LocID>
				<Text>精液量不足</Text>
			</GameDBLocalizedString>
			<GameDBLocalizedString>
				<LocID>SYM_SH_LOW_SEMEN_DESCRIPTION</LocID>
				<Text>患者报告射精（或精液）量异常减少。</Text>
			</GameDBLocalizedString>
			<GameDBLocalizedString>
				<LocID>SYM_SH_HYPOS</LocID>
				<Text>少精子症</Text>
			</GameDBLocalizedString>
			<GameDBLocalizedString>
				<LocID>SYM_SH_HYPOS_DESCRIPTION</LocID>
				<Text>检查结果显示患者患有少精子症。</Text>
			</GameDBLocalizedString>
			<GameDBLocalizedString>
				<LocID>SYM_SH_EPI</LocID>
				<Text>附睾炎</Text>
			</GameDBLocalizedString>
			<GameDBLocalizedString>
				<LocID>SYM_SH_EPI_DESCRIPTION</LocID>
				<Text>检查结果显示患者患有附睾炎。</Text>
			</GameDBLocalizedString>
			<GameDBLocalizedString>
				<LocID>SYM_SH_PHIMOSIS</LocID>
				<Text>包茎</Text>
			</GameDBLocalizedString>
			<GameDBLocalizedString>
				<LocID>SYM_SH_PHIMOSIS_DESCRIPTION</LocID>
				<Text>包皮过长是指包皮过紧，无法拉回阴茎头（龟头）。</Text>
			</GameDBLocalizedString>
			<GameDBLocalizedString>
				<LocID>SYM_SH_BAL</LocID>
				<Text>龟头炎</Text>
			</GameDBLocalizedString>
			<GameDBLocalizedString>
				<LocID>SYM_SH_BAL_DESCRIPTION</LocID>
				<Text>腹股沟检查显示患者患有包皮龟头炎。</Text>
			</GameDBLocalizedString>
			<GameDBLocalizedString>
				<LocID>SYM_SH_PRO</LocID>
				<Text>前列腺炎</Text>
			</GameDBLocalizedString>
			<GameDBLocalizedString>
				<LocID>SYM_SH_PRO_DESCRIPTION</LocID>
				<Text>检查结果显示患者患有前列腺炎。</Text>
			</GameDBLocalizedString>

			<!-- new -->

			<GameDBLocalizedString>
				<LocID>SYM_DER_NAIL_PITTING</LocID>
				<Text>甲板点状凹陷</Text>
			</GameDBLocalizedString>
			<GameDBLocalizedString>
				<LocID>SYM_DER_NAIL_PITTING_DESCRIPTION</LocID>
				<Text>甲板点状凹陷是甲板表面呈针点状凹陷，常见于银屑病或斑秃相关甲病变。</Text>
			</GameDBLocalizedString>
			<GameDBLocalizedString>
				<LocID>SYM_DER_PHOTOEXACERBATION</LocID>
				<Text>日晒加重</Text>
			</GameDBLocalizedString>
			<GameDBLocalizedString>
				<LocID>SYM_DER_PHOTOEXACERBATION_DESCRIPTION</LocID>
				<Text>日晒加重是皮损在日晒后加重，提示光敏/光加重性皮病，强化防晒与回避诱因有助控制。</Text>
			</GameDBLocalizedString>
			<GameDBLocalizedString>
				<LocID>SYM_DER_SYMMETRIC_MALAR_MACULES</LocID>
				<Text>对称性颧部色斑</Text>
			</GameDBLocalizedString>
			<GameDBLocalizedString>
				<LocID>SYM_DER_SYMMETRIC_MALAR_MACULES_DESCRIPTION</LocID>
				<Text>对称性颧部色斑是面部对称性分布的色素斑，多与黄褐斑相关；紫外线与激素水平变化常为诱因。</Text>
			</GameDBLocalizedString>
			<GameDBLocalizedString>
				<LocID>SYM_DER_FOREHEAD_INVOLVEMENT</LocID>
				<Text>额部受累</Text>
			</GameDBLocalizedString>
			<GameDBLocalizedString>
				<LocID>SYM_DER_FOREHEAD_INVOLVEMENT_DESCRIPTION</LocID>
				<Text>额部受累是面部对称性分布的色素斑，多与黄褐斑相关；紫外线与激素水平变化常为诱因。</Text>
			</GameDBLocalizedString>
			<GameDBLocalizedString>
				<LocID>SYM_DER_UPPERLIP_PATCH</LocID>
				<Text>上唇部色斑</Text>
			</GameDBLocalizedString>
			<GameDBLocalizedString>
				<LocID>SYM_DER_UPPERLIP_PATCH_DESCRIPTION</LocID>
				<Text>上唇部色斑是面部对称性分布的色素斑，多与黄褐斑相关；紫外线与激素水平变化常为诱因。</Text>
			</GameDBLocalizedString>
			<GameDBLocalizedString>
				<LocID>SYM_DER_KOEBNER</LocID>
				<Text>同形反应</Text>
			</GameDBLocalizedString>
			<GameDBLocalizedString>
				<LocID>SYM_DER_KOEBNER_DESCRIPTION</LocID>
				<Text>同形反应是在外伤/搔抓处出现与原病相同的新皮损，见于银屑病、扁平苔藓等。</Text>
			</GameDBLocalizedString>
			<GameDBLocalizedString>
				<LocID>SYM_DER_COLLARETTE_SCALE</LocID>
				<Text>领圈样鳞屑</Text>
			</GameDBLocalizedString>
			<GameDBLocalizedString>
				<LocID>SYM_DER_COLLARETTE_SCALE_DESCRIPTION</LocID>
				<Text>领圈样鳞屑是鳞屑呈内折项圈状，常见于玫瑰糠疹的‘先驱斑’及继发皮疹。</Text>
			</GameDBLocalizedString>
			<GameDBLocalizedString>
				<LocID>SYM_DER_PIH</LocID>
				<Text>炎症后色素沉着</Text>
			</GameDBLocalizedString>
			<GameDBLocalizedString>
				<LocID>SYM_DER_PIH_DESCRIPTION</LocID>
				<Text>炎症后色素沉着是炎症后色素改变，源于炎症介导的黑素代谢紊乱；控制原发病与防晒是关键。</Text>
			</GameDBLocalizedString>
			<GameDBLocalizedString>
				<LocID>SYM_DER_PIHYPO</LocID>
				<Text>炎症后色素减退</Text>
			</GameDBLocalizedString>
			<GameDBLocalizedString>
				<LocID>SYM_DER_PIHYPO_DESCRIPTION</LocID>
				<Text>炎症后色素减退是炎症后色素改变，源于炎症介导的黑素代谢紊乱；控制原发病与防晒是关键。</Text>
			</GameDBLocalizedString>
			<GameDBLocalizedString>
				<LocID>SYM_DER_SEBUM_EXCESS</LocID>
				<Text>皮脂分泌增多</Text>
			</GameDBLocalizedString>
			<GameDBLocalizedString>
				<LocID>SYM_DER_SEBUM_EXCESS_DESCRIPTION</LocID>
				<Text>皮脂分泌增多是皮脂分泌旺盛，常与痤疮、雄激素水平及遗传相关。</Text>
			</GameDBLocalizedString>
			<GameDBLocalizedString>
				<LocID>SYM_DER_SCALP_SCALE</LocID>
				<Text>头皮鳞屑</Text>
			</GameDBLocalizedString>
			<GameDBLocalizedString>
				<LocID>SYM_DER_SCALP_SCALE_DESCRIPTION</LocID>
				<Text>头皮鳞屑是头皮鳞屑增多，可见于脂溢性皮炎、头癣或银屑病，需结合KOH与临床表现鉴别。</Text>
			</GameDBLocalizedString>
			<GameDBLocalizedString>
				<LocID>SYM_DER_LICHENIFICATION</LocID>
				<Text>苔藓样变</Text>
			</GameDBLocalizedString>
			<GameDBLocalizedString>
				<LocID>SYM_DER_LICHENIFICATION_DESCRIPTION</LocID>
				<Text>苔藓样变是皮纹加深、皮肤增厚的慢性搔抓/摩擦改变，多见于慢性湿疹。</Text>
			</GameDBLocalizedString>
			<GameDBLocalizedString>
				<LocID>SYM_DER_EXCORIATIONS</LocID>
				<Text>抓痕/抓痕线</Text>
			</GameDBLocalizedString>
			<GameDBLocalizedString>
				<LocID>SYM_DER_EXCORIATIONS_DESCRIPTION</LocID>
				<Text>抓痕/抓痕线是因瘙痒搔抓形成的线状结痂/糜烂，常提示瘙痒性皮病活动。</Text>
			</GameDBLocalizedString>
			<GameDBLocalizedString>
				<LocID>SYM_DER_SATELLITE_PUSTULES</LocID>
				<Text>卫星样丘疹/脓疱</Text>
			</GameDBLocalizedString>
			<GameDBLocalizedString>
				<LocID>SYM_DER_SATELLITE_PUSTULES_DESCRIPTION</LocID>
				<Text>卫星样丘疹/脓疱是主病灶周围散在小丘疹/脓疱，常见于皮肤/黏膜念珠菌感染。</Text>
			</GameDBLocalizedString>
			<GameDBLocalizedString>
				<LocID>SYM_DER_ANNULAR_BORDER</LocID>
				<Text>环状隆起边缘</Text>
			</GameDBLocalizedString>
			<GameDBLocalizedString>
				<LocID>SYM_DER_ANNULAR_BORDER_DESCRIPTION</LocID>
				<Text>环状隆起边缘是环状红斑周边隆起、中央相对清亮的体征，提示体癣/股癣等浅表真菌病。</Text>
			</GameDBLocalizedString>
			<GameDBLocalizedString>
				<LocID>SYM_DER_CENTRAL_CLEARING</LocID>
				<Text>中央清亮</Text>
			</GameDBLocalizedString>
			<GameDBLocalizedString>
				<LocID>SYM_DER_CENTRAL_CLEARING_DESCRIPTION</LocID>
				<Text>中央清亮是皮损中心区域炎症消退、外观正常的现象，常见于体癣等皮肤真菌感染，形成典型的环状或多环状损害。</Text>
			</GameDBLocalizedString>
			<GameDBLocalizedString>
				<LocID>SYM_DER_ROSACEA_TRIGGERS_HOT_ALCOHOL</LocID>
				<Text>热饮/酒精诱发潮红</Text>
			</GameDBLocalizedString>
			<GameDBLocalizedString>
				<LocID>SYM_DER_ROSACEA_TRIGGERS_HOT_ALCOHOL_DESCRIPTION</LocID>
				<Text>患者在摄入热饮、辛辣食物或酒精后，面部出现短暂性红斑和灼热感，是玫瑰痤疮的常见诱发因素。</Text>
			</GameDBLocalizedString>
			<GameDBLocalizedString>
				<LocID>SYM_DER_PAPULOPUSTULES</LocID>
				<Text>丘疹脓疱</Text>
			</GameDBLocalizedString>
			<GameDBLocalizedString>
				<LocID>SYM_DER_PAPULOPUSTULES_DESCRIPTION</LocID>
				<Text>皮肤上同时出现红色炎性丘疹和含脓液的脓疱，是痤疮或玫瑰痤疮等炎症性皮肤病的典型皮损。</Text>
			</GameDBLocalizedString>
			<GameDBLocalizedString>
				<LocID>SYM_DER_GREASY_SCALE</LocID>
				<Text>油腻性鳞屑</Text>
			</GameDBLocalizedString>
			<GameDBLocalizedString>
				<LocID>SYM_DER_GREASY_SCALE_DESCRIPTION</LocID>
				<Text>附着于皮肤表面的黄色油腻性鳞屑，常见于头皮、面部等皮脂溢出部位，是脂溢性皮炎的特征性表现。</Text>
			</GameDBLocalizedString>
			<GameDBLocalizedString>
				<LocID>SYM_DER_NAIL_ONYCHOLYSIS</LocID>
				<Text>甲分离</Text>
			</GameDBLocalizedString>
			<GameDBLocalizedString>
				<LocID>SYM_DER_NAIL_ONYCHOLYSIS_DESCRIPTION</LocID>
				<Text>甲板从甲床远端或侧缘开始剥离，可见于银屑病、甲真菌病或外伤。</Text>
			</GameDBLocalizedString>
			<GameDBLocalizedString>
				<LocID>SYM_SH_LGV_NAAT_POS</LocID>
				<Text>沙眼衣原体L1–L3型核酸检测阳性</Text>
			</GameDBLocalizedString>
			<GameDBLocalizedString>
				<LocID>SYM_SH_LGV_NAAT_POS_DESCRIPTION</LocID>
				<Text>沙眼衣原体L1–L3型核酸检测阳性是核酸扩增试验检测出沙眼衣原体L1–L3型核酸，支持LGV诊断。</Text>
			</GameDBLocalizedString>
			<GameDBLocalizedString>
				<LocID>SYM_SH_DONOVAN_BODIES</LocID>
				<Text>涂片/活检见Donovan小体</Text>
			</GameDBLocalizedString>
			<GameDBLocalizedString>
				<LocID>SYM_SH_DONOVAN_BODIES_DESCRIPTION</LocID>
				<Text>涂片/活检见Donovan小体是涂片/活检见多诺万小体，提示腹股沟肉芽肿（多诺万病）。</Text>
			</GameDBLocalizedString>
			<GameDBLocalizedString>
				<LocID>SYM_SH_KOH_CANDIDA_POS</LocID>
				<Text>阴道分泌物10%KOH镜检见芽生酵母/假菌丝</Text>
			</GameDBLocalizedString>
			<GameDBLocalizedString>
				<LocID>SYM_SH_KOH_CANDIDA_POS_DESCRIPTION</LocID>
				<Text>阴道分泌物10%KOH镜检见芽生酵母/假菌丝是阴道分泌物KOH镜检见芽生酵母/假菌丝，符合念珠菌感染。</Text>
			</GameDBLocalizedString>
			<GameDBLocalizedString>
				<LocID>SYM_DER_COMEDONES</LocID>
				<Text>开放/闭合粉刺（黑头/白头）</Text>
			</GameDBLocalizedString>
			<GameDBLocalizedString>
				<LocID>SYM_DER_COMEDONES_DESCRIPTION</LocID>
				<Text>粉刺是痤疮的基本损害，由毛囊皮脂腺导管堵塞形成。开放性粉刺（黑头）因皮脂氧化及角质细胞内黑色素而呈黑色；闭合性粉刺（白头）则为肤色丘疹。</Text>
			</GameDBLocalizedString>
			<GameDBLocalizedString>
				<LocID>SYM_DER_CENTROFACIAL_TELANGIECTATIC_FLUSH</LocID>
				<Text>持续性中央面部潮红并可见毛细血管扩张</Text>
			</GameDBLocalizedString>
			<GameDBLocalizedString>
				<LocID>SYM_DER_CENTROFACIAL_TELANGIECTATIC_FLUSH_DESCRIPTION</LocID>
				<Text>面部中央（颊、鼻、额、颏）持续性红斑，伴有细小、扩张的浅表血管（毛细血管扩张），是红斑毛细血管扩张型玫瑰痤疮的典型特征。</Text>
			</GameDBLocalizedString>
			<GameDBLocalizedString>
				<LocID>SYM_DER_FLEXURAL_ECZEMA</LocID>
				<Text>屈侧湿疹样皮损伴显著瘙痒、苔藓样变</Text>
			</GameDBLocalizedString>
			<GameDBLocalizedString>
				<LocID>SYM_DER_FLEXURAL_ECZEMA_DESCRIPTION</LocID>
				<Text>肘窝、腘窝等屈侧部位出现湿疹样改变（红斑、鳞屑、渗出），常因剧烈瘙痒和长期搔抓导致皮肤增厚、皮纹加深（苔藓样变），是特应性皮炎的典型表现。</Text>
			</GameDBLocalizedString>
			<GameDBLocalizedString>
				<LocID>SYM_DER_TRANSIENT_WHEALS_24H</LocID>
				<Text>可压消、迁移性风团</Text>
			</GameDBLocalizedString>
			<GameDBLocalizedString>
				<LocID>SYM_DER_TRANSIENT_WHEALS_24H_DESCRIPTION</LocID>
				<Text>皮肤上出现暂时性、水肿性、红色或苍白的隆起斑块（风团），伴剧烈瘙痒，指压可褪色，通常在24小时内自行消退并在他处再发，是荨麻疹的特征性皮损。</Text>
			</GameDBLocalizedString>
			<GameDBLocalizedString>
				<LocID>SYM_DER_AUSPITZ_SIGN</LocID>
				<Text>去鳞后点状出血</Text>
			</GameDBLocalizedString>
			<GameDBLocalizedString>
				<LocID>SYM_DER_AUSPITZ_SIGN_DESCRIPTION</LocID>
				<Text>去鳞后点状出血是边界清楚的红斑鳞屑斑块与去鳞后点状出血，符合银屑病特征。</Text>
			</GameDBLocalizedString>
			<GameDBLocalizedString>
				<LocID>SYM_DER_WOOD_LAMP_DEPIGMENT</LocID>
				<Text>伍德灯下乳白荧光的脱色斑</Text>
			</GameDBLocalizedString>
			<GameDBLocalizedString>
				<LocID>SYM_DER_WOOD_LAMP_DEPIGMENT_DESCRIPTION</LocID>
				<Text>伍德灯下乳白荧光的脱色斑是伍德灯下呈乳白荧光，提示表皮黑素缺失（如白癜风）。</Text>
			</GameDBLocalizedString>
			<GameDBLocalizedString>
				<LocID>SYM_DER_KOH_DERMATOPHYTE_POS</LocID>
				<Text>皮屑边缘10–20%KOH镜检见透明分隔性菌丝</Text>
			</GameDBLocalizedString>
			<GameDBLocalizedString>
				<LocID>SYM_DER_KOH_DERMATOPHYTE_POS_DESCRIPTION</LocID>
				<Text>皮屑边缘10–20%KOH镜检见透明分隔性菌丝是KOH湿片可见透明分隔性菌丝，提示皮肤癣菌感染。</Text>
			</GameDBLocalizedString>
			<GameDBLocalizedString>
				<LocID>SYM_DER_KOH_DERMATOPHYTE_POS_GROIN</LocID>
				<Text>腹股沟皮屑KOH镜检阳性</Text>
			</GameDBLocalizedString>
			<GameDBLocalizedString>
				<LocID>SYM_DER_KOH_DERMATOPHYTE_POS_GROIN_DESCRIPTION</LocID>
				<Text>腹股沟皮屑KOH镜检阳性是KOH湿片可见透明分隔性菌丝，提示皮肤癣菌感染。</Text>
			</GameDBLocalizedString>
			<GameDBLocalizedString>
				<LocID>SYM_DER_BLACK_DOT_TCAP</LocID>
				<Text>黑点样脱发（断发）或KOH毛发检查阳性</Text>
			</GameDBLocalizedString>
			<GameDBLocalizedString>
				<LocID>SYM_DER_BLACK_DOT_TCAP_DESCRIPTION</LocID>
				<Text>黑点样脱发（断发）或KOH毛发检查阳性是毛发断裂遗留黑点样外观，常见于头癣内毛型感染。</Text>
			</GameDBLocalizedString>
			<GameDBLocalizedString>
				<LocID>SYM_DER_SPAGHETTI_MEATBALLS_KOH</LocID>
				<Text>皮屑KOH示短丝+酵母团</Text>
			</GameDBLocalizedString>
			<GameDBLocalizedString>
				<LocID>SYM_DER_SPAGHETTI_MEATBALLS_KOH_DESCRIPTION</LocID>
				<Text>皮屑KOH示短丝+酵母团是KOH下可见短丝与成团酵母（‘意大利面+肉丸’），典型于花斑癣。</Text>
			</GameDBLocalizedString>
			<GameDBLocalizedString>
				<LocID>SYM_DER_THROMBOSED_CAPILLARIES</LocID>
				<Text>刮削后见黑点/点状出血</Text>
			</GameDBLocalizedString>
			<GameDBLocalizedString>
				<LocID>SYM_DER_THROMBOSED_CAPILLARIES_DESCRIPTION</LocID>
				<Text>刮削后见黑点/点状出血是刮除角质后可见点状黑点/出血，为疣体内血栓化毛细血管所致。</Text>
			</GameDBLocalizedString>
			<GameDBLocalizedString>
				<LocID>SYM_DER_FLAT_WARTS_CLUSTERS</LocID>
				<Text>面/手/腿多发细小扁平丘疹成群</Text>
			</GameDBLocalizedString>
			<GameDBLocalizedString>
				<LocID>SYM_DER_FLAT_WARTS_CLUSTERS_DESCRIPTION</LocID>
				<Text>面/手/腿多发细小扁平丘疹成群是多发细小扁平丘疹成簇，符合扁平疣表现。</Text>
			</GameDBLocalizedString>
			<GameDBLocalizedString>
				<LocID>SYM_DER_HONEY_COLORED_CRUSTS</LocID>
				<Text>蜂蜜色痂</Text>
			</GameDBLocalizedString>
			<GameDBLocalizedString>
				<LocID>SYM_DER_HONEY_COLORED_CRUSTS_DESCRIPTION</LocID>
				<Text>蜂蜜色痂是金黄蜂蜜色痂，典型见于脓疱疮。</Text>
			</GameDBLocalizedString>
			<GameDBLocalizedString>
				<LocID>SYM_DER_HERALD_PATCH</LocID>
				<Text>‘先驱斑’+随后圣诞树样分布</Text>
			</GameDBLocalizedString>
			<GameDBLocalizedString>
				<LocID>SYM_DER_HERALD_PATCH_DESCRIPTION</LocID>
				<Text>‘先驱斑’+随后圣诞树样分布是首先出现的较大椭圆形鳞屑斑，数日后全身出现‘圣诞树’样分布的继发皮疹。</Text>
			</GameDBLocalizedString>
			<GameDBLocalizedString>
				<LocID>SYM_DER_EXCLAMATION_MARK_HAIR</LocID>
				<Text>脱发边缘‘感叹号样毛’</Text>
			</GameDBLocalizedString>
			<GameDBLocalizedString>
				<LocID>SYM_DER_EXCLAMATION_MARK_HAIR_DESCRIPTION</LocID>
				<Text>脱发边缘‘感叹号样毛’是近端变细、远端粗的短断发，边缘呈“感叹号”样，提示斑秃活动。</Text>
			</GameDBLocalizedString>
			<GameDBLocalizedString>
				<LocID>SYM_DER_WICKHAM_STRIAE</LocID>
				<Text>皮损表面Wickham网状白纹</Text>
			</GameDBLocalizedString>
			<GameDBLocalizedString>
				<LocID>SYM_DER_WICKHAM_STRIAE_DESCRIPTION</LocID>
				<Text>皮损表面Wickham网状白纹是皮损表面细致的网状白纹，为扁平苔藓特征体征。</Text>
			</GameDBLocalizedString>
			<GameDBLocalizedString>
				<LocID>SYM_DER_DH_IGA_DIF_POS</LocID>
				<Text>直接免疫荧光是乳头真皮颗粒状IgA沉积</Text>
			</GameDBLocalizedString>
			<GameDBLocalizedString>
				<LocID>SYM_DER_DH_IGA_DIF_POS_DESCRIPTION</LocID>
				<Text>直接免疫荧光是乳头真皮颗粒状IgA沉积是直接免疫荧光示乳头真皮颗粒状IgA沉积，支持疱疹样皮炎诊断。</Text>
			</GameDBLocalizedString>
			<GameDBLocalizedString>
				<LocID>SYM_DER_MELASMA_WOODLAMP_ENHANCE</LocID>
				<Text>伍德灯提示表皮型色沉增强</Text>
			</GameDBLocalizedString>
			<GameDBLocalizedString>
				<LocID>SYM_DER_MELASMA_WOODLAMP_ENHANCE_DESCRIPTION</LocID>
				<Text>伍德灯提示表皮型色沉增强是伍德灯下色斑边界与色度增强，提示主要为表皮型色沉。</Text>
			</GameDBLocalizedString>
			<GameDBLocalizedString>
				<LocID>SYM_DER_HS_SINUS_TRACTS</LocID>
				<Text>腋/腹股沟反复结节脓肿并窦道/瘘道形成</Text>
			</GameDBLocalizedString>
			<GameDBLocalizedString>
				<LocID>SYM_DER_HS_SINUS_TRACTS_DESCRIPTION</LocID>
				<Text>腋/腹股沟反复结节脓肿并窦道/瘘道形成是反复结节脓肿后形成的皮下窦道与瘢痕，为化脓性汗腺炎的慢性改变。</Text>
			</GameDBLocalizedString>
			<GameDBLocalizedString>
				<LocID>SYM_DER_SEBDERM_SEBORRHEIC_PLAQUES</LocID>
				<Text>脂溢区油腻性鳞屑性红斑</Text>
			</GameDBLocalizedString>
			<GameDBLocalizedString>
				<LocID>SYM_DER_SEBDERM_SEBORRHEIC_PLAQUES_DESCRIPTION</LocID>
				<Text>脂溢区油腻性鳞屑性红斑是面部/胸背等脂溢部位油腻性鳞屑性红斑，提示脂溢性皮炎。</Text>
			</GameDBLocalizedString>
			<GameDBLocalizedString>
				<LocID>SYM_DER_SCABIES_BURROWS</LocID>
				<Text>指缝/腕屈侧可见疥螨隧道</Text>
			</GameDBLocalizedString>
			<GameDBLocalizedString>
				<LocID>SYM_DER_SCABIES_BURROWS_DESCRIPTION</LocID>
				<Text>指缝/腕屈侧可见疥螨隧道是指缝、腕屈侧等处可见细长曲折隧道样线条，多伴剧痒，提示疥疮。</Text>
			</GameDBLocalizedString>

		</LocalizedStrings>
	</GameDBStringTable>
</Database>
